mql5_zmq_backtrader/__init__.py
mql5_zmq_backtrader/adapter.py
mql5_zmq_backtrader/cli.py
mql5_zmq_backtrader/mql5_zmq_backtrader.py
mql5_zmq_backtrader/mt5broker.py
mql5_zmq_backtrader/mt5data.py
mql5_zmq_backtrader/mt5store.py
mql5_zmq_backtrader-0.1.1.dist-info/AUTHORS.rst
mql5_zmq_backtrader-0.1.1.dist-info/LICENSE
mql5_zmq_backtrader-0.1.1.dist-info/METADATA
mql5_zmq_backtrader-0.1.1.dist-info/WHEEL
mql5_zmq_backtrader-0.1.1.dist-info/entry_points.txt
mql5_zmq_backtrader-0.1.1.dist-info/top_level.txt
mql5_zmq_backtrader-0.1.1.dist-info/RECORD
