Metadata-Version: 2.1
Name: mql5-zmq-backtrader
Version: 0.1.1
Summary: Project developed to work as a server for Python trading community. It is based on ZeroMQ sockets and uses JSON format to communicate messages. It is a python library for the ZeroMQ API within backtrader framework. It allows rapid trading algo development. For details of API behavior, please see the online API document.
Home-page: https://github.com/parrondo/mql5_zmq_backtrader
Author: R. Martin Parrondo
Author-email: audreyr@example.com
License: MIT license
Keywords: mql5_zmq_backtrader
Platform: UNKNOWN
Classifier: Development Status :: 2 - Pre-Alpha
Classifier: Intended Audience :: Developers
Classifier: License :: OSI Approved :: MIT License
Classifier: Natural Language :: English
Classifier: Programming Language :: Python :: 3
Classifier: Programming Language :: Python :: 3.5
Classifier: Programming Language :: Python :: 3.6
Classifier: Programming Language :: Python :: 3.7
Classifier: Programming Language :: Python :: 3.8
Requires-Python: >=3.5
Requires-Dist: Click (>=7.0)
